MANIFEST.in
README.rst
setup.py
collective/__init__.py
collective.contactauthor.egg-info/PKG-INFO
collective.contactauthor.egg-info/SOURCES.txt
collective.contactauthor.egg-info/dependency_links.txt
collective.contactauthor.egg-info/entry_points.txt
collective.contactauthor.egg-info/namespace_packages.txt
collective.contactauthor.egg-info/not-zip-safe
collective.contactauthor.egg-info/requires.txt
collective.contactauthor.egg-info/top_level.txt
collective/contactauthor/__init__.py
collective/contactauthor/configure.zcml
collective/contactauthor/interfaces.py
collective/contactauthor/setuphandlers.py
collective/contactauthor/testing.py
collective/contactauthor/tests.py
collective/contactauthor/upgrades.zcml
collective/contactauthor/vocabularies.py
collective/contactauthor/Extensions/install.py
collective/contactauthor/browser/__init__.py
collective/contactauthor/browser/configure.zcml
collective/contactauthor/browser/controlpanel.py
collective/contactauthor/browser/status.py
collective/contactauthor/browser/resources/Security-Captcha-icon.png
collective/contactauthor/locales/collective.contactauthor.pot
collective/contactauthor/locales/manual.pot
collective/contactauthor/locales/run18ndude.sh
collective/contactauthor/locales/it/LC_MESSAGES/collective.contactauthor.po
collective/contactauthor/profiles/default/browserlayer.xml
collective/contactauthor/profiles/default/controlpanel.xml
collective/contactauthor/profiles/default/metadata.xml
collective/contactauthor/profiles/default/registry.xml
collective/contactauthor/profiles/default/rolemap.xml
collective/contactauthor/profiles/default/skins.xml
collective/contactauthor/profiles/uninstall/browserlayer.xml
collective/contactauthor/profiles/uninstall/controlpanel.xml
collective/contactauthor/profiles/uninstall/registry.xml
collective/contactauthor/profiles/uninstall/skins.xml
collective/contactauthor/skins/contact_author/author.cpt
collective/contactauthor/skins/contact_author/author.cpt.metadata
collective/contactauthor/skins/contact_author/send_feedback.cpy
collective/contactauthor/skins/contact_author/send_feedback.cpy.metadata
collective/contactauthor/skins/contact_author/validate_feedback.vpy
docs/HISTORY.rst
docs/INSTALL.txt
docs/LICENSE.GPL
docs/LICENSE.txt