Metadata-Version: 1.0
Name: collective.contactauthor
Version: 1.1.0
Summary: A customization for Plone author form: anonymous users can send message to authors with captcha protection
Home-page: http://plone.org/products/collective.contactauthor
Author: RedTurtle Technology
Author-email: sviluppoplone@redturtle.it
License: GPL
Keywords: plone plonegov captcha author e-mail contact
Platform: UNKNOWN
Classifier: Framework :: Plone
Classifier: Framework :: Plone :: 3.3
Classifier: Framework :: Plone :: 4.0
Classifier: Framework :: Plone :: 4.2
Classifier: Framework :: Plone :: 4.3
Classifier: Programming Language :: Python
